LICENSE.txt
README.rst
setup.py
tests.py
nbp/__init__.py
nbp/models.py
nbp/table.py
nbp/utils.py
nbp.egg-info/PKG-INFO
nbp.egg-info/SOURCES.txt
nbp.egg-info/dependency_links.txt
nbp.egg-info/not-zip-safe
nbp.egg-info/top_level.txt