Metadata-Version: 1.0
Name: nbp
Version: 1.0
Summary: Polish National Bank currency rate downloader.
Home-page: https://github.com/jqb/python-nbp/tree/ver-1.0
Author: Kuba Janoszek
Author-email: kuba.janoszek@gmail.com
License: UNKNOWN
Platform: UNKNOWN
Classifier: Development Status :: 4 - Beta
Classifier: Environment :: Web Environment
Classifier: Intended Audience :: Developers
Classifier: License :: OSI Approved :: BSD License
Classifier: Operating System :: OS Independent
Classifier: Programming Language :: Python
